pyrandom/__init__.py
pyrandom/data.py
pyrandom/generators.py
pyrandom/randoms.py
randpy/__init__.py
randpy/data.py
randpy/generators.py
randpy/randoms.py
randpy-0.1.1.dist-info/DESCRIPTION.rst
randpy-0.1.1.dist-info/METADATA
randpy-0.1.1.dist-info/RECORD
randpy-0.1.1.dist-info/WHEEL
randpy-0.1.1.dist-info/metadata.json
randpy-0.1.1.dist-info/top_level.txt
