Metadata-Version: 2.0
Name: randpy
Version: 0.1.1
Summary: Tiny set of utilities to generate random data
Home-page: https://github.com/mattshaffer11/randpy
Author: Matt Shaffer
Author-email: mattshaffer11@gmail.com
License: MIT
Keywords: testing data random
Platform: UNKNOWN
Classifier: Development Status :: 3 - Alpha
Classifier: Intended Audience :: Developers
Classifier: License :: OSI Approved :: MIT License
Classifier: Programming Language :: Python :: 2
Classifier: Programming Language :: Python :: 2.7
Classifier: Programming Language :: Python :: 3
Classifier: Programming Language :: Python :: 3.4
Classifier: Programming Language :: Python :: 3.5
Classifier: Programming Language :: Python :: 3.6
Requires-Python: >=2.6, !=3.0.*, !=3.1.*, !=3.2.*, <4
